axonclient/__init__.py
axonclient/client.py
axonclient/exceptions.py
axonclient/protos/__init__.py
axonclient/protos/command_pb2.py
axonclient/protos/command_pb2.pyi
axonclient/protos/command_pb2_grpc.py
axonclient/protos/common_pb2.py
axonclient/protos/common_pb2.pyi
axonclient/protos/common_pb2_grpc.py
axonclient/protos/control_pb2.py
axonclient/protos/control_pb2.pyi
axonclient/protos/control_pb2_grpc.py
axonclient/protos/event_pb2.py
axonclient/protos/event_pb2.pyi
axonclient/protos/event_pb2_grpc.py
axonclient/protos/query_pb2.py
axonclient/protos/query_pb2.pyi
axonclient/protos/query_pb2_grpc.py
axonclient/py.typed
axonclient-0.1.2.dist-info/LICENSE
axonclient-0.1.2.dist-info/WHEEL
axonclient-0.1.2.dist-info/METADATA
axonclient-0.1.2.dist-info/RECORD
