Metadata-Version: 2.1
Name: axonclient
Version: 0.1.2
Summary: Python client for Axon Server
Home-page: https://github.com/pyeventsourcing/axonclient
License: BSD 3-Clause
Author: John Bywater
Author-email: john.bywater@appropriatesoftware.net
Requires-Python: >=3.7,<4.0
Classifier: Development Status :: 3 - Alpha
Classifier: License :: OSI Approved :: BSD License
Classifier: License :: Other/Proprietary License
Classifier: Programming Language :: Python
Classifier: Programming Language :: Python :: 3
Classifier: Programming Language :: Python :: 3.10
Classifier: Programming Language :: Python :: 3.7
Classifier: Programming Language :: Python :: 3.8
Classifier: Programming Language :: Python :: 3.9
Requires-Dist: grpcio (>=1.44.0,<1.45.0)
Requires-Dist: protobuf (>=3.20.0,<3.21.0)
Project-URL: Repository, https://github.com/pyeventsourcing/axonclient
